pypowerbi/__init__.py
pypowerbi/activity_logs.py
pypowerbi/base.py
pypowerbi/client.py
pypowerbi/credentials.py
pypowerbi/dataset.py
pypowerbi/datasets.py
pypowerbi/enums.py
pypowerbi/features.py
pypowerbi/gateway.py
pypowerbi/gateways.py
pypowerbi/group.py
pypowerbi/group_user.py
pypowerbi/groups.py
pypowerbi/import_class.py
pypowerbi/imports.py
pypowerbi/report.py
pypowerbi/reports.py
pypowerbi/utils.py
pypowerbi-0.27.dist-info/LICENSE
pypowerbi-0.27.dist-info/METADATA
pypowerbi-0.27.dist-info/WHEEL
pypowerbi-0.27.dist-info/top_level.txt
pypowerbi-0.27.dist-info/RECORD
