Metadata-Version: 2.1
Name: pypowerbi
Version: 0.27
Summary: A python library for Microsoft's PowerBI
Home-page: http://github.com/cmberryau/pypowerbi
Author: Chris Berry
Author-email: chris@chrisberry.com.au
License: MIT
Platform: UNKNOWN
Requires-Dist: requests
Requires-Dist: adal
Requires-Dist: future-fstrings
